relevanceai/__init__.py
relevanceai/_api/__init__.py
relevanceai/_api/api_client.py
relevanceai/_api/batch/__init__.py
relevanceai/_api/batch/chunk.py
relevanceai/_api/batch/insert.py
relevanceai/_api/batch/local_logger.py
relevanceai/_api/batch/retrieve.py
relevanceai/_api/endpoints/__init__.py
relevanceai/_api/endpoints/api_client.py
relevanceai/_api/endpoints/admin/__init__.py
relevanceai/_api/endpoints/admin/admin.py
relevanceai/_api/endpoints/datasets/__init__.py
relevanceai/_api/endpoints/datasets/datasets.py
relevanceai/_api/endpoints/datasets/documents.py
relevanceai/_api/endpoints/datasets/field_children.py
relevanceai/_api/endpoints/datasets/monitor.py
relevanceai/_api/endpoints/datasets/tasks.py
relevanceai/_api/endpoints/datasets/cluster/__init__.py
relevanceai/_api/endpoints/datasets/cluster/cluster.py
relevanceai/_api/endpoints/datasets/cluster/centroids/__init__.py
relevanceai/_api/endpoints/datasets/cluster/centroids/centroids.py
relevanceai/_api/endpoints/deployables/__init__.py
relevanceai/_api/endpoints/deployables/deployables.py
relevanceai/_api/endpoints/services/__init__.py
relevanceai/_api/endpoints/services/aggregate.py
relevanceai/_api/endpoints/services/cluster.py
relevanceai/_api/endpoints/services/prediction.py
relevanceai/_api/endpoints/services/recommend.py
relevanceai/_api/endpoints/services/search.py
relevanceai/_api/endpoints/services/services.py
relevanceai/_api/endpoints/services/tagger.py
relevanceai/_api/endpoints/workflows/__init__.py
relevanceai/_api/endpoints/workflows/workflows.py
relevanceai/apps/__init__.py
relevanceai/apps/explorer_app/__init__.py
relevanceai/apps/explorer_app/app.py
relevanceai/apps/explorer_app/auto.py
relevanceai/apps/explorer_app/base.py
relevanceai/apps/report_app/__init__.py
relevanceai/apps/report_app/app.py
relevanceai/apps/report_app/base.py
relevanceai/apps/report_app/blocks.py
relevanceai/apps/report_app/marks.py
relevanceai/apps/report_app/advanced_blocks/__init__.py
RelevanceAI_dev-3.2.22.2023.1.3.0.10.55.984477.dist-info/LICENSE
RelevanceAI_dev-3.2.22.2023.1.3.0.10.55.984477.dist-info/METADATA
RelevanceAI_dev-3.2.22.2023.1.3.0.10.55.984477.dist-info/WHEEL
RelevanceAI_dev-3.2.22.2023.1.3.0.10.55.984477.dist-info/top_level.txt
RelevanceAI_dev-3.2.22.2023.1.3.0.10.55.984477.dist-info/RECORD
